[
    {
      "id": 1,
      "img_url": "https://mtv.mtvnimages.com/uri/mgid:file:http:shared:mtv.com/news/wp-content/uploads/2017/04/1-1491840068.png?quality=.8&height=600&width=800"
    },
    {
      "id": 2,
      "img_url": "https://mtv.mtvnimages.com/uri/mgid:file:http:shared:mtv.com/news/wp-content/uploads/2017/04/2-1491840203.jpg?quality=.8&height=540&width=708"
    },
    {
      "id": 3,
      "img_url": "https://mtv.mtvnimages.com/uri/mgid:file:http:shared:mtv.com/news/wp-content/uploads/2017/04/3-1491840243.png?quality=.8&height=540&width=720"
    },
    {
      "id": 4,
      "img_url": "https://mtv.mtvnimages.com/uri/mgid:file:http:shared:mtv.com/news/wp-content/uploads/2017/04/Zombies_are_real_Zombie_Island-1491840163.png?quality=.8&height=600.4181184668989&width=800"
    },
    {
      "id": 5,
      "img_url": "https://mtv.mtvnimages.com/uri/mgid:file:http:shared:mtv.com/news/wp-content/uploads/2017/04/Ghost_of_Mr._Hyde-1491841015.png?quality=.8&height=540&width=720"
    },
    {
      "id": 6,
      "img_url": "https://mtv.mtvnimages.com/uri/mgid:file:http:shared:mtv.com/news/wp-content/uploads/2017/04/mummu-1491841071.jpg?quality=.8&height=600.695894224078&width=800"
    },
    {
      "id": 7,
      "img_url": "https://mtv.mtvnimages.com/uri/mgid:file:http:shared:mtv.com/news/wp-content/uploads/2017/04/Scooby-Doo-1491841275.jpg?quality=.8&height=516.4889253486465&width=800"
    },
    {
      "id": 8,
      "img_url": "https://mtv.mtvnimages.com/uri/mgid:file:http:shared:mtv.com/news/wp-content/uploads/2017/04/Revolta-1491841331.png?quality=.8&height=480&width=640"
    },
    {
      "id": 9,
      "img_url": "https://mtv.mtvnimages.com/uri/mgid:file:http:shared:mtv.com/news/wp-content/uploads/2017/04/Scooby-Doo2-1491841401.jpg?quality=.8&height=502&width=784"
    },
    {
      "id": 10,
      "img_url": "https://mtv.mtvnimages.com/uri/mgid:file:http:shared:mtv.com/news/wp-content/uploads/2017/04/Creepy_Sarah_Ravencroft-1491841456.jpg?quality=.8&height=380&width=500"
    },
    {
      "id": 11,
      "img_url": "https://mtv.mtvnimages.com/uri/mgid:file:http:shared:mtv.com/news/wp-content/uploads/2017/04/Scooby-Doo3-1491841635.jpg?quality=.8&height=399&width=667"
    },
    {
      "id": 12,
      "img_url": "https://mtv.mtvnimages.com/uri/mgid:file:http:shared:mtv.com/news/wp-content/uploads/2017/04/Scooby-Doo-1491841794.jpg?quality=.8&height=574.3157894736842&width=800"
    }
  ]